kami_logging/.pypi_token
kami_logging/__init__.py
kami_logging/kami_logging.py
kami_logging-0.2.1.dist-info/LICENSE
kami_logging-0.2.1.dist-info/METADATA
kami_logging-0.2.1.dist-info/WHEEL
kami_logging-0.2.1.dist-info/RECORD
