Metadata-Version: 2.1
Name: kami-logging
Version: 0.2.1
Summary: Simple logging and benckmark decorator
Author: Maicon de Menezes
Author-email: maicondmenezes@gmail.com
Requires-Python: >=3.9,<4.0
Classifier: Programming Language :: Python :: 3
Classifier: Programming Language :: Python :: 3.9
Classifier: Programming Language :: Python :: 3.10
Classifier: Programming Language :: Python :: 3.11
